LICENSE
MANIFEST.in
README.md
requirements.txt
setup.cfg
setup.py
rareplantfinder/__init__.py
rareplantfinder/rareplantfinder.py
rareplantfinder.egg-info/PKG-INFO
rareplantfinder.egg-info/SOURCES.txt
rareplantfinder.egg-info/dependency_links.txt
rareplantfinder.egg-info/not-zip-safe
rareplantfinder.egg-info/top_level.txt